alubia/__init__.py
alubia/data.py
alubia/exceptions.py
alubia/ingest.py
alubia/pdf.py
alubia/tests/__init__.py
alubia/tests/test_data.py
alubia-2025.12.8.dist-info/METADATA
alubia-2025.12.8.dist-info/WHEEL
alubia-2025.12.8.dist-info/licenses/COPYING
alubia-2025.12.8.dist-info/RECORD
