Metadata-Version: 2.4
Name: alubia
Version: 2025.12.8
Summary: Bits and bobs for beancount benefit.
Project-URL: Homepage, https://github.com/Julian/alubia
Project-URL: Issues, https://github.com/Julian/alubia/issues/
Project-URL: Funding, https://github.com/sponsors/Julian
Project-URL: Source, https://github.com/Julian/alubia
Author-email: Julian Berman <Julian+alubia@GrayVines.com>
License-Expression: MIT
License-File: COPYING
Keywords: accounting,beancount,finance
Classifier: Development Status :: 3 - Alpha
Classifier: Operating System :: OS Independent
Classifier: Programming Language :: Python
Classifier: Programming Language :: Python :: 3
Classifier: Programming Language :: Python :: 3.13
Classifier: Programming Language :: Python :: 3.14
Classifier: Programming Language :: Python :: Implementation :: CPython
Classifier: Programming Language :: Python :: Implementation :: PyPy
Requires-Python: >=3.14
Requires-Dist: attrs>=25.4.0
Requires-Dist: rpds-py>=0.29.0
Provides-Extra: pdf
Requires-Dist: pymupdf; extra == 'pdf'
